[{
    "id": 1,
    "name": "CitiFinder",
    "skills": "Javascript",
    "image": "./assets/portfolio1.png",
    "keypoint": "Event Handlers",
    "github": "https://github.com/drewwoods55/cityFinder",
    "link": "https://drewwoods55.github.io/cityFinder/"
},
{
    "id": 1,
    "name": "CitiFinder",
    "skills": "Javascript",
    "image": "./assets/portfolio1.png",
    "keypoint": "Event Handlers",
    "github": "https://github.com/drewwoods55/cityFinder",
    "link": "https://drewwoods55.github.io/cityFinder/"
},

{
    "id": 1,
    "name": "CitiFinder",
    "skills": "Javascript",
    "image": "./assets/portfolio1.png",
    "keypoint": "Event Handlers",
    "github": "https://github.com/drewwoods55/cityFinder",
    "link": "https://drewwoods55.github.io/cityFinder/"
},

{
    "id": 1,
    "name": "CitiFinder",
    "skills": "Javascript",
    "image": "./assets/portfolio1.png",
    "keypoint": "Event Handlers",
    "github": "https://github.com/drewwoods55/cityFinder",
    "link": "https://drewwoods55.github.io/cityFinder/"
},

{
    "id": 1,
    "name": "CitiFinder",
    "skills": "Javascript",
    "image": "./assets/portfolio1.png",
    "keypoint": "Event Handlers",
    "github": "https://github.com/drewwoods55/cityFinder",
    "link": "https://drewwoods55.github.io/cityFinder/"
},



]